{
  "$schema": "http://json-schema.org/draft-07/schema#",
  "$id": "insights/v1/events/honeybadger-laravel/redis.executed.json",
  "title": "Laravel: redis.executed",
  "description": "A Redis command was executed.",
  "x-hb": {
    "notifiers": ["honeybadger-laravel"],
    "category": "database",
    "component": "Redis"
  },
  "type": "object",
  "properties": {
    "event_type": {
      "type": "string",
      "const": "redis.executed"
    },
    "connectionName": {
      "type": "string",
      "description": "Redis connection name.",
      "examples": [
        "default"
      ]
    },
    "command": {
      "type": "string",
      "description": "Formatted Redis command with parameters.",
      "examples": [
        "get users:123"
      ]
    },
    "duration": {
      "type": "number",
      "description": "Duration in microseconds. The client sends a value with an ms suffix, such as \"5.123ms\". The ingestion pipeline converts it to microseconds.",
      "examples": [
        450
      ]
    },
    "requestId": {
      "type": "string",
      "description": "Correlation ID for the request, set by the AssignRequestId middleware via Laravel's shared log context. The value comes from the Request-Id or X-Request-Id request header, or is a generated UUID. Present only when that middleware is enabled.",
      "examples": [
        "f3b2c1d0-4e5a-4b6c-8d7e-9f0a1b2c3d4e"
      ]
    }
  },
  "required": [
    "event_type",
    "connectionName",
    "command"
  ]
}
